supersafepackage/__init__.py
supersafepackage-4.0.1.dist-info/METADATA
supersafepackage-4.0.1.dist-info/WHEEL
supersafepackage-4.0.1.dist-info/top_level.txt
supersafepackage-4.0.1.dist-info/RECORD
