Metadata-Version: 2.4
Name: supersafepackage
Version: 4.0.1
Summary: Malicious demo package
Dynamic: summary
